score_regression/__init__.py
score_regression/_version.py
score_regression/score_regression.py
score_regression/tests/__init__.py
score_regression/tests/test_common.py
score_regression/tests/test_template.py
score_regression-0.0.23.dist-info/LICENSE
score_regression-0.0.23.dist-info/METADATA
score_regression-0.0.23.dist-info/WHEEL
score_regression-0.0.23.dist-info/top_level.txt
score_regression-0.0.23.dist-info/RECORD
