Metadata-Version: 2.1
Name: score-regression
Version: 0.0.23
Summary: A classifier that maximizes AUC
Home-page: https://github.com/hrolfrc/score_regression
Download-URL: https://github.com/hrolfrc/score_regression
Maintainer: Carlson Research, LLC
Maintainer-email: hrolfrc@gmail.com
License: new BSD
Classifier: Intended Audience :: Science/Research
Classifier: Intended Audience :: Developers
Classifier: Topic :: Scientific/Engineering :: Artificial Intelligence
Classifier: Topic :: Scientific/Engineering :: Mathematics
Classifier: Development Status :: 2 - Pre-Alpha
Classifier: License :: OSI Approved
Classifier: Topic :: Scientific/Engineering
Classifier: Operating System :: OS Independent
Classifier: Programming Language :: Python :: 3
License-File: LICENSE
Requires-Dist: numpy
Requires-Dist: scipy
Requires-Dist: scikit-learn
Provides-Extra: docs
Requires-Dist: sphinx ; extra == 'docs'
Requires-Dist: sphinx-gallery ; extra == 'docs'
Requires-Dist: sphinx-rtd-theme ; extra == 'docs'
Requires-Dist: numpydoc ; extra == 'docs'
Requires-Dist: matplotlib ; extra == 'docs'
Provides-Extra: tests
Requires-Dist: pytest ; extra == 'tests'
Requires-Dist: pytest-cov ; extra == 'tests'
